{
  "realm": "a2a-local",
  "enabled": true,
  "clients": [
    {
      "clientId": "website-client",
      "enabled": true,
      "publicClient": false,
      "secret": "website-client-secret",
      "directAccessGrantsEnabled": true,
      "standardFlowEnabled": false,
      "serviceAccountsEnabled": false,
      "protocol": "openid-connect"
    },
    {
      "clientId": "identity-facade",
      "enabled": true,
      "publicClient": false,
      "secret": "identity-facade-secret",
      "serviceAccountsEnabled": true,
      "directAccessGrantsEnabled": false,
      "standardFlowEnabled": false,
      "protocol": "openid-connect"
    },
    {
      "clientId": "discovery-agent",
      "enabled": true,
      "publicClient": false,
      "secret": "discovery-agent-secret",
      "serviceAccountsEnabled": true,
      "directAccessGrantsEnabled": false,
      "standardFlowEnabled": false,
      "protocol": "openid-connect"
    },
    {
      "clientId": "classifier-agent",
      "enabled": true,
      "publicClient": false,
      "secret": "classifier-agent-secret",
      "serviceAccountsEnabled": true,
      "directAccessGrantsEnabled": false,
      "standardFlowEnabled": false,
      "protocol": "openid-connect"
    },
    {
      "clientId": "assessor-agent",
      "enabled": true,
      "publicClient": false,
      "secret": "assessor-agent-secret",
      "serviceAccountsEnabled": true,
      "directAccessGrantsEnabled": false,
      "standardFlowEnabled": false,
      "protocol": "openid-connect"
    },
    {
      "clientId": "router-agent",
      "enabled": true,
      "publicClient": false,
      "secret": "router-agent-secret",
      "serviceAccountsEnabled": true,
      "directAccessGrantsEnabled": false,
      "standardFlowEnabled": false,
      "protocol": "openid-connect"
    },
    {
      "clientId": "handler-agent",
      "enabled": true,
      "publicClient": false,
      "secret": "handler-agent-secret",
      "serviceAccountsEnabled": true,
      "directAccessGrantsEnabled": false,
      "standardFlowEnabled": false,
      "protocol": "openid-connect"
    },
    {
      "clientId": "api-backend-agent",
      "enabled": true,
      "publicClient": false,
      "secret": "api-backend-agent-secret",
      "serviceAccountsEnabled": true,
      "directAccessGrantsEnabled": false,
      "standardFlowEnabled": false,
      "protocol": "openid-connect"
    }
  ]
}
